debm/FitMultiGame.py
debm/Model.py
debm/Models.py
debm/Prospect.py
debm/__init__.py
debm/classes.py
debm/debm.py
debm/makeGrid.py
debm/resPlot.py
debm/saveEstimation.py
DEBM-0.2.3.dist-info/METADATA
DEBM-0.2.3.dist-info/WHEEL
DEBM-0.2.3.dist-info/top_level.txt
DEBM-0.2.3.dist-info/RECORD
