Metadata-Version: 2.1
Name: DEBM
Version: 0.2.3
Summary: A package for modeling behavior in decision from experience experiments
Home-page: UNKNOWN
Author: Ofir Yakobi
Author-email: <debm.package@gmail.com>
License: UNKNOWN
Keywords: modeling,academic
Platform: UNKNOWN
Classifier: Development Status :: 4 - Beta
Classifier: Intended Audience :: Education
Classifier: Programming Language :: Python :: 2
Classifier: Programming Language :: Python :: 3
Classifier: Operating System :: MacOS :: MacOS X
Classifier: Operating System :: Microsoft :: Windows
Requires-Dist: numpy
Requires-Dist: pandas
Requires-Dist: scipy
Requires-Dist: matplotlib
Requires-Dist: tqdm
Requires-Dist: openpyxl
Requires-Dist: xlrd
